rmscene/__init__.py
rmscene/__main__.py
rmscene/crdt_sequence.py
rmscene/py.typed
rmscene/scene_items.py
rmscene/scene_stream.py
rmscene/scene_tree.py
rmscene/tagged_block_common.py
rmscene/tagged_block_reader.py
rmscene/tagged_block_writer.py
rmscene/text.py
rmscene-0.7.0.dist-info/LICENSE
rmscene-0.7.0.dist-info/METADATA
rmscene-0.7.0.dist-info/WHEEL
rmscene-0.7.0.dist-info/RECORD
